pyflowy-0.0.1.dist-info/WHEEL
pyflowy-0.0.1.dist-info/RECORD
pyflowy-0.0.1.dist-info/METADATA
pyflowy/__init__.py
pyflowy/util.py
pyflowy/flowycpp.cpython-312-x86_64-linux-musl.so
pyflowy.libs/libgcc_s-a04fdf82.so.1
pyflowy.libs/libstdc++-a9383cce.so.6.0.28
