Metadata-Version: 2.1
Name: pyflowy
Version: 0.0.1
Summary: Python bindings for flowy
Author-Email: Amrita Goswami <amrita16thaug646@gmail.com>, Moritz Sallermann <moritzsallermann@gmail.com>, Rohit Goswami <rgoswami@ieee.org>
License: GPL v3
Requires-Python: >=3.9
Requires-Dist: numpy>=1.26.4
Requires-Dist: pybind11>=2.12.0
